iclone/__init__.py
icolor/__init__.py
iprint/__init__.py
icecomet_test-0.0.11.dist-info/LICENSE
icecomet_test-0.0.11.dist-info/METADATA
icecomet_test-0.0.11.dist-info/WHEEL
icecomet_test-0.0.11.dist-info/top_level.txt
icecomet_test-0.0.11.dist-info/RECORD
