Metadata-Version: 2.1
Name: icecomet-test
Version: 0.0.11
Summary: debug
Home-page: https://github.com/yourusername/my_library
Author: icecomet
Author-email: icecomet634@gmail.com
License: MIT
Classifier: Programming Language :: Python :: 3
Classifier: License :: OSI Approved :: MIT License
Classifier: Operating System :: OS Independent
Requires-Python: >=3.6
License-File: LICENSE
